smort_query/__init__.py
smort_query/object_query.py
smort_query-1.2.0.dist-info/LICENSE
smort_query-1.2.0.dist-info/METADATA
smort_query-1.2.0.dist-info/WHEEL
smort_query-1.2.0.dist-info/top_level.txt
smort_query-1.2.0.dist-info/RECORD
