Metadata-Version: 2.1
Name: smort-query
Version: 1.2.0
Summary: Django like query engine for any objects.
Home-page: https://github.com/matiuszka/smort-query
Author: Mateusz Nowak
Author-email: nowak.mateusz@hotmail.com
License: MIT
Platform: UNKNOWN
Classifier: Development Status :: 5 - Production/Stable
Classifier: License :: OSI Approved :: MIT License
Classifier: Programming Language :: Python :: 3.6
Classifier: Programming Language :: Python :: 3.7
Classifier: Programming Language :: Python :: 3.8
Classifier: Programming Language :: Python :: 3.9
Classifier: Programming Language :: Python :: 3.10
Requires-Python: >=3.6
License-File: LICENSE
Requires-Dist: more-itertools (~=8.0)
